{
    "add_is_visible": true,
    "category": "visual elements",
    "default_dim": {
        "height": 600,
        "width": 600
    },
    "display": "Jitsi",
    "events": {
        "AAN": {
            "caption": "a participant joined the meeting",
            "doc": "Indicates when a new participant has joined the meeting",
            "name": "participant_joined"
        },
        "AAO": {
            "caption": "a participant left the meeting",
            "doc": "Indicated when a participant has left the meeting",
            "name": "participant_left"
        },
        "AAP": {
            "caption": "requires password",
            "doc": "",
            "name": "password_required"
        },
        "AAQ": {
            "caption": "is ready to close",
            "name": "ready_to_close"
        },
        "AAR": {
            "caption": "videoconference joined",
            "name": "videoconference_joined"
        },
        "AAS": {
            "caption": "videoconference left",
            "name": "videoconference_left"
        },
        "AAT": {
            "caption": "displayname change",
            "name": "displayname_change"
        },
        "AAU": {
            "caption": "email change",
            "name": "email_change"
        },
        "AAV": {
            "caption": "avatar URL change",
            "name": "avatarurl_change"
        },
        "AAs": {
            "caption": "audio mute status changed",
            "name": "audiomute_status_changed"
        },
        "AAv": {
            "caption": "video mute status changed",
            "name": "videomute_status_changed"
        }
    },
    "has_reset_fn": true,
    "icon": "ion-ios-videocam",
    "property_applications": {
        "Border": true,
        "BoxShadow": true,
        "MinWidth": true,
        "resizable": true
    },
    "states": {
        "AAD": {
            "caption": "number of participants",
            "doc": "Number of participants",
            "initialization_code": {
                "fn": "function(properties, context) {\n\n\treturn 0;\n}"
            },
            "name": "number_of_participants",
            "value": "number"
        },
        "AAE": {
            "caption": "on meeting",
            "doc": "Is there an active meeting?",
            "initialization_code": {
                "fn": "function(properties, context) {\n\n\treturn false;\n}"
            },
            "name": "on_meeting",
            "value": "boolean"
        },
        "AAF": {
            "caption": "meeting Id",
            "doc": "ID of the meeting",
            "initialization_code": {
                "fn": "function(properties, context) {\n    \n \treturn '';\n}"
            },
            "name": "meeting_id",
            "value": "text"
        },
        "AAG": {
            "caption": "local_role",
            "initialization_code": {
                "fn": "function(properties, context) {\n\n\treturn '';\n}"
            },
            "name": "local_role",
            "value": "text"
        },
        "AAH": {
            "caption": "participant Id",
            "initialization_code": {
                "fn": "function(properties, context) {\n\n\treturn 0;\n}"
            },
            "name": "participant_id",
            "value": "text"
        },
        "AAI": {
            "caption": "user id",
            "initialization_code": {
                "fn": "function(properties, context) {\n\n\treturn '';\n}"
            },
            "name": "user_id",
            "value": "text"
        },
        "AAJ": {
            "caption": "participant display name",
            "doc": "Name to be displayed for the participant",
            "initialization_code": {
                "fn": "function(properties, context) {\n\n\treturn '';\n}"
            },
            "name": "participant_displayname",
            "value": "text"
        },
        "AAK": {
            "caption": "participant email",
            "doc": "Email of the participant",
            "initialization_code": {
                "fn": "function(properties, context) {\n\n\treturn '';\n}"
            },
            "name": "participant_email",
            "value": "text"
        },
        "AAL": {
            "caption": "participant evatar url",
            "initialization_code": {
                "fn": "function(properties, context) {\n\n\treturn '';\n}"
            },
            "name": "participant_avatarurl",
            "value": "text"
        },
        "AAM": {
            "caption": "jitsi ready",
            "initialization_code": {
                "fn": "function(properties, context) {\n\n\treturn false;\n}"
            },
            "name": "jitsi_ready",
            "value": "boolean"
        },
        "AAt": {
            "caption": "audio muted",
            "doc": "Indicates whether the microphone is currently muted",
            "initialization_code": {
                "fn": "function(properties, context) {\n    \n}"
            },
            "name": "audio_muted",
            "value": "boolean"
        },
        "AAu": {
            "caption": "video muted",
            "doc": "Indicates whether the camera is currently muted",
            "initialization_code": {
                "fn": "function(properties, context) {\n\n}"
            },
            "name": "video_muted",
            "value": "boolean"
        }
    }
}